transform_h4nnah/__init__.py
transform_h4nnah/calculator.py
transform_h4nnah-0.0.1.dist-info/METADATA
transform_h4nnah-0.0.1.dist-info/WHEEL
transform_h4nnah-0.0.1.dist-info/licenses/LICENCE
transform_h4nnah-0.0.1.dist-info/RECORD
