Metadata-Version: 2.4
Name: transform_h4nnah
Version: 0.0.1
Summary: Koordinaatide konvertor.
Project-URL: Homepage, https://github.com/pypa/sampleproject
Project-URL: Issues, https://github.com/pypa/sampleproject/issues
Author-email: Hannah Mänd <hannah@python.com>
License-Expression: MIT
License-File: LICENCE
Classifier: Operating System :: OS Independent
Classifier: Programming Language :: Python :: 3
Requires-Python: >=3.8
